lifeguard_openai/__init__.py
lifeguard_openai/settings.py
lifeguard_openai/actions/__init__.py
lifeguard_openai/actions/errors.py
lifeguard_openai/infrastructure/__init__.py
lifeguard_openai/infrastructure/prompt.py
lifeguard_openai-1.0.5.dist-info/METADATA
lifeguard_openai-1.0.5.dist-info/WHEEL
lifeguard_openai-1.0.5.dist-info/top_level.txt
lifeguard_openai-1.0.5.dist-info/RECORD
